{"cameraMode":{"drawMode":0,"name":"Shaded","section":"Shading Mode"},"sceneLighting":true,"audioPlay":false,"sceneViewState":{"showFog":true,"showMaterialUpdate":false,"showSkybox":true,"showFlares":true,"showImageEffects":true,"showParticleSystems":true,"showVisualEffectGraphs":true,"m_FxEnabled":true},"in2DMode":false,"pivot":{"x":4.932482719421387,"y":-0.7034530639648438,"z":28.4061336517334},"rotation":{"x":0.03439560905098915,"y":0.07638100534677506,"z":-0.00260111503303051,"w":0.9965061545372009},"size":17.59894371032715,"orthographic":false}